scrapli_ssh2/__init__.py
scrapli_ssh2/transport/__init__.py
scrapli_ssh2/transport/cssh2.py
tests/__init__.py
tests/unit/__init__.py
tests/unit/transport/__init__.py
tests/unit/transport/test_cssh2.py
scrapli_ssh2-2020.10.24.dist-info/LICENSE
scrapli_ssh2-2020.10.24.dist-info/METADATA
scrapli_ssh2-2020.10.24.dist-info/WHEEL
scrapli_ssh2-2020.10.24.dist-info/top_level.txt
scrapli_ssh2-2020.10.24.dist-info/RECORD
