Metadata-Version: 2.1
Name: scrapli-ssh2
Version: 2020.10.24
Summary: ssh2-python transport plugin for the scrapli SSH|Telnet screen scraping library
Home-page: https://github.com/scrapli/scrapli_ssh2
Author: Carl Montanari
Author-email: carl.r.montanari@gmail.com
License: UNKNOWN
Platform: UNKNOWN
Classifier: License :: OSI Approved :: MIT License
Classifier: Programming Language :: Python :: 3
Classifier: Programming Language :: Python :: 3.6
Classifier: Programming Language :: Python :: 3.7
Classifier: Programming Language :: Python :: 3.8
Classifier: Programming Language :: Python :: 3.9
Classifier: Operating System :: POSIX :: Linux
Classifier: Operating System :: MacOS
Requires-Python: >=3.6
Requires-Dist: ssh2-python (<1.0.0,>=0.23.0)
Requires-Dist: scrapli (>=2020.10.10)
